vw_executor/__init__.py
vw_executor/artifacts.py
vw_executor/handlers.py
vw_executor/loggers.py
vw_executor/pool.py
vw_executor/vw.py
vw_executor/vw_cache.py
vw_executor/vw_opts.py
vw_executor-0.1.6.dist-info/METADATA
vw_executor-0.1.6.dist-info/WHEEL
vw_executor-0.1.6.dist-info/top_level.txt
vw_executor-0.1.6.dist-info/RECORD
